tfbs_footprinter/__init__.py
tfbs_footprinter/__main__.py
tfbs_footprinter/tfbs_footprinter.2019-01-29.py
tfbs_footprinter/tfbs_footprinter.bak.py
tfbs_footprinter/tfbs_footprinter.most_current.bak.py
tfbs_footprinter/tfbs_footprinter.pcloud_downloaded.py
tfbs_footprinter/tfbs_footprinter.pre-chroms.py
tfbs_footprinter/tfbs_footprinter.py
TFBS_footprinting-1.0.0b54.dist-info/LICENSE
TFBS_footprinting-1.0.0b54.dist-info/METADATA
TFBS_footprinting-1.0.0b54.dist-info/WHEEL
TFBS_footprinting-1.0.0b54.dist-info/entry_points.txt
TFBS_footprinting-1.0.0b54.dist-info/top_level.txt
TFBS_footprinting-1.0.0b54.dist-info/RECORD
