Metadata-Version: 2.1
Name: TFBS-footprinting
Version: 1.0.0b54
Summary: Tool for identifying conserved TFBSs in vertebrate species.
Home-page: https://github.com/thirtysix/TFBS_footprinting
Author: Harlan Barker
Author-email: harlan.barker@tuni.fi
License: MIT
Keywords: bioinformatics analysis
Platform: UNKNOWN
Classifier: Development Status :: 4 - Beta
Classifier: Intended Audience :: Science/Research
Classifier: Topic :: Scientific/Engineering :: Bio-Informatics
Classifier: License :: OSI Approved :: MIT License
Classifier: Programming Language :: Python :: 2
Classifier: Programming Language :: Python :: 2.6
Classifier: Programming Language :: Python :: 2.7
Requires-Dist: httplib2
Requires-Dist: numpy
Requires-Dist: matplotlib
Requires-Dist: biopython
Requires-Dist: msgpack
Requires-Dist: wget
